inspyred_print/__init__.py
inspyred_print/version.py
inspyred_print-1.2.1.dist-info/WHEEL
inspyred_print-1.2.1.dist-info/METADATA
inspyred_print-1.2.1.dist-info/RECORD
